{
  "id": 10297,
  "vip": false,
  "style": 2,
  "themeColor": "#FFB042",
  "textBlackColor": "#2C2D2F",
  "textWhiteColor": "#FFFFFF",
  "dividerColor": "#33000000",
  "backgroundRes": null,
  "backAlign": 3,
  "weightFive": 2.77,
  "weightFour": 2.45,
  "weightSix": 2.56,
  "top": {
    "changeByTheme": true,
    "textColor": "#2C2D2F",
    "titleTextColor": "#000000",
    "titleThemeColor": false,
    "logoTextColor": "#FFFFFF",
    "logoBgRes": "shape_tem_logo_bg_white",
    "headBgRes": "tem_head_10297",
    "head1Style": 0
  },
  "item": {
    "textColor": "#2C2D2F",
    "titleTextColor": "#FFFFFF",
    "chartBottomDivColor": "#1A000000",
    "chartDivColor": "#FFEBBF",
    "chartHightLightColor": "#1AFFD169",
    "chartNormalColor": "#FFFFFF",
    "changeByTheme": true,
    "chartHightLightByTheme": true,
    "itemTextBold": false,
    "itemTopOuterLine": false,
    "itemListOuterLine": false,
    "itemBottomBlock": true,
    "itemBottomLine": true,
    "itemBottomToDividerColor": false
  }
}